LICENSE
README.md
setup.py
some_random_python.egg-info/PKG-INFO
some_random_python.egg-info/SOURCES.txt
some_random_python.egg-info/dependency_links.txt
some_random_python.egg-info/top_level.txt
somerandom/__init__.py
somerandom/api.py
somerandom/endpoints.py
somerandom/request.py