Metadata-Version: 2.1
Name: some-random-python
Version: 2.0
Summary: Simple wrapper for some-random-api.
Home-page: https://github.com/MagM1go/smr
Author: MagMigo
License: UNKNOWN
Platform: UNKNOWN
Classifier: Programming Language :: Python :: 3.10
Classifier: License :: OSI Approved :: MIT License
Classifier: Operating System :: OS Independent
Requires-Python: >=3.7
License-File: LICENSE
